cmpe240 lab/Lab5/source.v
`timescale 1ns/1ns
module source(y,n,s,i,rst,clk);

  output reg [1:0] y;
  output reg [1:0] n;
  output reg [1:0] s;
  input wire [1:0] i;
  input wire rst;
  input wire clk;

  always @(s,i) begin
	y[0]=a'b+s[1]s[0]+s[1]b;
	y[1]=s1'a+s0'ab';
	n[0]=s0'b+s1s0+s1b;
	n[1]=y[1]
    end
    // Sync reset
  always @(posedge clk) begin
    if (rst)
    s <= 2'b00;
    else
    s <= n;
  end
endmodule

cmpe240 lab/Lab5/code/test_bench.v
`timescale 1ns/1ns
module testbench();

  wire [1:0] y;
  wire [1:0] n;
  wire [1:0] s;

  reg clk;
  initial clk = 1;
  always #2 clk = ~clk;

  reg rst;
  initial rst = 1;

  reg [1:0]bar;
  initial bar = 2'b00;
	
	
	always @(posedge clk) begin
	#47
	bar[0] = ~bar[0];
	end
	
	always @(posedge clk) begin
	#55
	bar[1] = ~bar[1];
	end
	
  source fsm_tester(y, n, s, bar, rst, clk);

  initial begin
    $dumpfile("TimingDiagram.vcd");
    $dumpvars(0, y, n, s, bar, rst, clk);
	#15
    rst = 0;
	#4000
    $finish;
  end
endmodule

BS/cmpe240 lab/Lab5/code/TimingDiagram.vcd
$date
	Wed May 16 12:02:06 2018
$end
$version
	Icarus Verilog
$end
$timescale
	1ns
$end
$scope module testbench $end
$var wire 2 ! y [1:0] $end
$upscope $end
$scope module testbench $end
$var wire 2 " n [1:0] $end
$upscope $end
$scope module testbench $end
$var wire 2 # s [1:0] $end
$upscope $end
$scope module testbench $end
$var reg 2 $ bar [1:0] $end
$upscope $end
$scope module testbench $end
$var reg 1 % rst $end
$upscope $end
$scope module testbench $end
$var reg 1 & clk $end
$upscope $end
$enddefinitions $end
#0
$dumpvars
1&
1%
b0 $
b0 #
b0 "
b0 !
$end
#2
0&
#4
1&
#6
0&
#8
1&
#10
0&
#12
1&
#14
0&
#15
0%
#16
1&
#18
0&
#20
1&
#22
0&
#24
1&
#26
0&
#28
1&
#30
0&
#32
1&
#34
0&
#36
1&
#38
0&
#40
1&
#42
0&
#44
1&
#46
0&
#48
1&
#50
0&
#51
b1 "
b1 !
b1 $
#52
b0 "
b1 #
1&
#54
0&
#56
b1 "
b0 #
1&
#58
0&
#59
b11 "
b10 !
b11 $
#60
b1 "
b1 !
b11 #
1&
#62
0&
#64
b10 "
b10 !
b1 #
1&
#66
0&
#68
b1 "
b1 !
b10 #
1&
#70
0&
#72
b10 "
b10 !
b1 #
1&
#74
0&
#76
b1 "
b1 !
b10 #
1&
#78
0&
#80
b10 "
b10 !
b1 #
1&
#82
0&
#84
b1 "
b1 !
b10 #
1&
#86
0&
#88
b10 "
b10 !
b1 #
1&
#90
0&
#92
b1 "
b1 !
b10 #
1&
#94
0&
#96
b10 "
b10 !
b1 #
1&
#98
0&
#99
b10 $
#100
b10 #
1&
#102
0&
#104
1&
#106
0&
#108
1&
#110
0&
#112
1&
#114
0&
#115
b0 "
b0 !
b0 $
#116
b0 #
1&
#118
0&
#120
1&
#122
0&
#124
1&
#126
0&
#128
1&
#130
0&
#132
1&
#134
0&
#136
1&
#138
0&
#140
1&
#142
0&
#144
1&
#146
0&
#147
b1 "
b1 !
b1 $
#148
b0 "
b1 #
1&
#150
0&
#152
b1 "
b0 #
1&
#154
0&
#156
b0 "
b1 #
1&
#158
0&
#160
b1 "
b0 #
1&
#162
0&
#164
b0 "
b1 #
1&
#166
0&
#168
b1 "
b0 #
1&
#170
0&
#171
b11 "
b10 !
b11 $
#172
b1 "
b1 !
b11 #
1&
#174
0&
#176
b10 "
b10 !
b1 #
1&
#178
0&
#180
b1 "
b1 !
b10 #
1&
#182
0&
#184
b10 "
b10 !
b1 #
1&
#186
0&
#188
b1 "
b1 !
b10 #
1&
#190
0&
#192
b10 "
b10 !
b1 #
1&
#194
0&
#195
b10 $
#196
b10 #
1&
#198
0&
#200
1&
#202
0&
#204
1&
#206
0&
#208
1&
#210
0&
#212
1&
#214
0&
#216
1&
#218
0&
#220
1&
#222
0&
#224
1&
#226
0&
#227
b0 "
b0 !
b0 $
#228
b0 #
1&
#230
0&
#232
1&
#234
0&
#236
1&
#238
0&
#240
1&
#242
0&
#243
b1 "
b1 !
b1 $
#244
b0 "
b1 #
1&
#246
0&
#248
b1 "
b0 #
1&
#250
0&
#252
b0 "
b1 #
1&
#254
0&
#256
b1 "
b0 #
1&
#258
0&
#260
b0 "
b1 #
1&
#262
0&
#264
b1 "
b0 #
1&
#266
0&
#268
b0 "
b1 #
1&
#270
0&
#272
b1 "
b0 #
1&
#274
0&
#276
b0 "
b1 #
1&
#278
0&
#280
b1 "
b0 #
1&
#282
0&
#283
b11 "
b10 !
b11 $
#284
b1 "
b1 !
b11 #
1&
#286
0&
#288
b10 "
b10 !
b1 #
1&
#290
0&
#291
b10 $
#292
b10 #
1&
#294
0&
#296
1&
#298
0&
#300
1&
#302
0&
#304
1&
#306
0&
#308
1&
#310
0&
#312
1&
#314
0&
#316
1&
#318
0&
#320
1&
#322
0&
#324
1&
#326
0&
#328
1&
#330
0&
#332
1&
#334
0&
#336
1&
#338
0&
#339
b1 "
b1 !
b1 $
#340
b0 "
b1 #
1&
#342
0&
#344
b1 "
b0 #
1&
#346
0&
#348
b0 "
b1 #
1&
#350
0&
#352
b1 "
b0 #
1&
#354
0&
#356
b0 "
b1 #
1&
#358
0&
#360
b1 "
b0 #
1&
#362
0&
#364
b0 "
b1 #
1&
#366
0&
#368
b1 "
b0 #
1&
#370
0&
#372
b0 "
b1 #
1&
#374
0&
#376
b1 "
b0 #
1&
#378
0&
#380
b0 "
b1 #
1&
#382
0&
#384
b1 "
b0 #
1&
#386
0&
#387
b0 "
b0 !
b0 $
#388
1&
#390
0&
#392
1&
#394
0&
#395
b10 "
b10 !
b10 $
#396
b10 #
1&
#398
0&
#400
1&
#402
0&
#404
1&
#406
0&
#408
1&
#410
0&
#412
1&
#414
0&
#416
1&
#418
0&
#420
1&
#422
0&
#424
1&
#426
0&
#428
1&
#430
0&
#432
1&
#434
0&
#435
b1 "
b1 !
b11 $
#436
b10 "
b10 !
b1 #
1&
#438
0&
#440
b1 "
b1 !
b10 #
1&
#442
0&
#444
b10 "
b10 !
b1 #
1&
#446
0&
#448
b1 "
b1 !
b10 #
1&
#450
0&
#451
b1 $
#452
b0 "
b1 #
1&
#454
0&
#456
b1 "
b0 #
1&
#458
0&
#460
b0 "
b1 #
1&
#462
0&
#464
b1 "
b0 #
1&
#466
0&
#468
b0 "
b1 #
1&
#470
0&
#472
b1 "
b0 #
1&
#474
0&
#476
b0 "
b1 #
1&
#478
0&
#480
b1 "
b0 #
1&
#482
0&
#483
b0 "
b0 !
b0 $
#484
1&
#486
0&
#488
1&
#490
0&
#492
1&
#494
0&
#496
1&
#498
0&
#500
1&
#502
0&
#504
1&
#506
0&
#507
b10 "
b10 !
b10 $
#508
b10 #
1&
#510
0&
#512
1&
#514
0&
#516
1&
#518
0&
#520
1&
#522
0&
#524
1&
#526
0&
#528
1&
#530
0&
#531
b1 "
b1 !
b11 $
#532
b10 "
b10 !
b1 #
1&
#534
0&
#536
b1 "
b1 !
b10 #
1&
#538
0&
#540
b10 "
b10 !
b1 #
1&
#542
0&
#544
b1 "
b1 !
b10 #
1&
#546
0&
#548
b10 "
b10 !
b1 #
1&
#550
0&
#552
b1 "
b1 !
b10 #
1&
#554
0&
#556
b10 "
b10 !
b1 #
1&
#558
0&
#560
b1 "
b1 !
b10 #
1&
#562
0&
#563
b1 $
#564
b0 "
b1 #
1&
#566
0&
#568
b1 "
b0 #
1&
#570
0&
#572
b0 "
b1 #
1&
#574
0&
#576
b1 "
b0 #
1&
#578
0&
#579
b0 "
b0 !
b0 $
#580
1&
#582
0&
#584
1&
#586
0&
#588
1&
#590
0&
#592
1&
#594
0&
#596
1&
#598
0&
#600
1&
#602
0&
#604
1&
#606
0&
#608
1&
#610
0&
#612
1&
#614
0&
#616
1&
#618
0&
#619
b10 "
b10 !
b10 $
#620
b10 #
1&
#622
0&
#624
1&
#626
0&
#627
b1 "
b1 !
b11 $
#628
b10 "
b10 !
b1 #
1&
#630
0&
#632
b1 "
b1 !
b10 #
1&
#634
0&
#636
b10 "
b10 !
b1 #
1&
#638
0&
#640
b1 "
b1 !
b10 #
1&
#642
0&
#644
b10 "
b10 !
b1 #
1&
#646
0&
#648
b1 "
b1 !
b10 #
1&
#650
0&
#652
b10 "
b10 !
b1 #
1&
#654
0&
#656
b1 "
b1 !
b10 #
1&
#658
0&
#660
b10 "
b10 !
b1 #
1&
#662
0&
#664
b1 "
b1 !
b10 #
1&
#666
0&
#668
b10 "
b10 !
b1 #
1&
#670
0&
#672
b1 "
b1 !
b10 #
1&
#674
0&
#675
b0 "
b0 !
b0 $
#676
b0 #
1&
#678
0&
#680
1&
#682
0&
#684
1&
#686
0&
#688
1&
#690
0&
#692
1&
#694
0&
#696
1&
#698
0&
#700
1&
#702
0&
#704
1&
#706
0&
#708
1&
#710
0&
#712
1&
#714
0&
#716
1&
#718
0&
#720
1&
#722
0&
#723
b1 "
b1 !
b1 $
#724
b0 "
b1 #
1&
#726
0&
#728
b1 "
b0 #
1&
#730
0&
#731
b11 "
b10 !
b11 $
#732
b1 "
b1 !
b11 #
1&
#734
0&
#736
b10 "
b10 !
b1 #
1&
#738
0&
#740
b1 "
b1 !
b10 #
1&
#742
0&
#744
b10 "
b10 !
b1 #
1&
#746
0&
#748
b1 "
b1 !
b10 #
1&
#750
0&
#752
b10 "
b10 !
b1 #
1&
#754
0&
#756
b1 "
b1 !
b10 #
1&
#758
0&
#760
b10 "
b10 !
b1 #
1&
#762
0&
#764
b1 "
b1 !
b10 #
1&
#766
0&
#768
b10 "
b10 !
b1 #
1&
#770
0&
#771
b10 $
#772
b10 #
1&
#774
0&
#776
1&
#778
0&
#780
1&
#782
0&
#784
1&
#786
0&
#787
b0 "
b0 !
b0 $
#788
b0 #
1&
#790
0&
#792
1&
#794
0&
#796
1&
#798
0&
#800
1&
#802
0&
#804
1&
#806
0&
#808
1&
#810
0&
#812
1&
#814
0&
#816
1&
#818
0&
#819
b1 "
b1 !
b1 $
#820
b0 "
b1 #
1&
#822
0&
#824
b1 "
b0 #
1&
#826
0&
#828
b0 "
b1 #
1&
#830
0&
#832
b1 "
b0 #
1&
#834
0&
#836
b0 "
b1 #
1&
#838
0&
#840
b1 "
b0 #
1&
#842
0&
#843
b11 "
b10 !
b11 $
#844
b1 "
b1 !
b11 #
1&
#846
0&
#848
b10 "
b10 !
b1 #
1&
#850
0&
#852
b1 "
b1 !
b10 #
1&
#854
0&
#856
b10 "
b10 !
b1 #
1&
#858
0&
#860
b1 "
b1 !
b10 #
1&
#862
0&
#864
b10 "
b10 !
b1 #
1&
#866
0&
#867
b10 $
#868
b10 #
1&
#870
0&
#872
1&
#874
0&
#876
1&
#878
0&
#880
1&
#882
0&
#884
1&
#886
0&
#888
1&
#890
0&
#892
1&
#894
0&
#896
1&
#898
0&
#899
b0 "
b0 !
b0 $
#900
b0 #
1&
#902
0&
#904
1&
#906
0&
#908
1&
#910
0&
#912
1&
#914
0&
#915
b1 "
b1 !
b1 $
#916
b0 "
b1 #
1&
#918
0&
#920
b1 "
b0 #
1&
#922
0&
#924
b0 "
b1 #
1&
#926
0&
#928
b1 "
b0 #
1&
#930
0&
#932
b0 "
b1 #
1&
#934
0&
#936
b1 "
b0 #
1&
#938
0&
#940
b0 "
b1 #
1&
#942
0&
#944
b1 "
b0 #
1&
#946
0&
#948
b0 "
b1 #
1&
#950
0&
#952
b1 "
b0 #
1&
#954
0&
#955
b11 "
b10 !
b11 $
#956
b1 "
b1 !
b11 #
1&
#958
0&
#960
b10 "
b10 !
b1 #
1&
#962
0&
#963
b10 $
#964
b10 #
1&
#966
0&
#968
1&
#970
0&
#972
1&
#974
0&
#976
1&
#978
0&
#980
1&
#982
0&
#984
1&
#986
0&
#988
1&
#990
0&
#992
1&
#994
0&
#996
1&
#998
0&
#1000
1&
#1002
0&
#1004
1&
#1006
0&
#1008
1&
#1010
0&
#1011
b1 "
b1 !
b1 $
#1012
b0 "
b1 #
1&
#1014
0&
#1016
b1 "
b0 #
1&
#1018
0&
#1020
b0 "
b1 #
1&
#1022
0&
#1024
b1 "
b0 #
1&
#1026
0&
#1028
b0 "
b1 #
1&
#1030
0&
#1032
b1 "
b0 #
1&
#1034
0&
#1036
b0 "
b1 #
1&
#1038
0&
#1040
b1 "
b0 #
1&
#1042
0&
#1044
b0 "
b1 #
1&
#1046
0&
#1048
b1 "
b0 #
1&
#1050
0&
#1052
b0 "
b1 #
1&
#1054
0&
#1056
b1 "
b0 #
1&
#1058
0&
#1059
b0 "
b0 !
b0 $
#1060
1&
#1062
0&
#1064
1&
#1066
0&
#1067
b10 "
b10 !
b10 $
#1068
b10 #
1&
#1070
0&
#1072
1&
#1074
0&
#1076
1&
#1078
0&
#1080
1&
#1082
0&
#1084
1&
#1086
0&
#1088
1&
#1090
0&
#1092
1&
#1094
0&
#1096
1&
#1098
0&
#1100
1&
#1102
0&
#1104
1&
#1106
0&
#1107
b1 "
b1 !
b11 $
#1108
b10 "
b10 !
b1 #
1&
#1110
0&
#1112
b1 "
b1 !
b10 #
1&
#1114
0&
#1116
b10 "
b10 !
b1 #
1&
#1118
0&
#1120
b1 "
b1 !
b10 #
1&
#1122
0&
#1123
b1 $
#1124
b0 "
b1 #
1&
#1126
0&
#1128
b1 "
b0 #
1&
#1130
0&
#1132
b0 "
b1 #
1&
#1134
0&
#1136
b1 "
b0 #
1&
#1138
0&
#1140
b0 "
b1 #
1&
#1142
0&
#1144
b1 "
b0 #
1&
#1146
0&
#1148
b0 "
b1 #
1&
#1150
0&
#1152
b1 "
b0 #
1&
#1154
0&
#1155
b0 "
b0 !
b0 $
#1156
1&
#1158
0&
#1160
1&
#1162
0&
#1164
1&
#1166
0&
#1168
1&
#1170
0&
#1172
1&
#1174
0&
#1176
1&
#1178
0&
#1179
b10 "
b10 !
b10 $
#1180
b10 #
1&
#1182
0&
#1184
1&
#1186
0&
#1188
1&
#1190
0&
#1192
1&
#1194
0&
#1196
1&
#1198
0&
#1200
1&
#1202
0&
#1203
b1 "
b1 !
b11 $
#1204
b10 "
b10 !
b1 #
1&
#1206
0&
#1208
b1 "
b1 !
b10 #
1&
#1210
0&
#1212
b10 "
b10 !
b1 #
1&
#1214
0&
#1216
b1 "
b1 !
b10 #
1&
#1218
0&
#1220
b10 "
b10 !
b1 #
1&
#1222
0&
#1224
b1 "
b1 !
b10 #
1&
#1226
0&
#1228
b10 "
b10 !
b1 #
1&
#1230
0&
#1232
b1 "
b1 !
b10 #
1&
#1234
0&
#1235
b1 $
#1236
b0 "
b1 #
1&
#1238
0&
#1240
b1 "
b0 #
1&
#1242
0&
#1244
b0 "
b1 #
1&
#1246
0&
#1248
b1 "
b0 #
1&
#1250
0&
#1251
b0 "
b0 !
b0 $
#1252
1&
#1254
0&
#1256
1&
#1258
0&
#1260
1&
#1262
0&
#1264
1&
#1266
0&
#1268
1&
#1270
0&
#1272
1&
#1274
0&
#1276
1&
#1278
0&
#1280
1&
#1282
0&
#1284
1&
#1286
0&
#1288
1&
#1290
0&
#1291
b10 "
b10 !
b10 $
#1292
b10 #
1&
#1294
0&
#1296
1&
#1298
0&
#1299
b1 "
b1 !
b11 $
#1300
b10 "
b10 !
b1 #
1&
#1302
0&
#1304
b1 "
b1 !
b10 #
1&
#1306
0&
#1308
b10 "
b10 !
b1 #
1&
#1310
0&
#1312
b1 "
b1 !
b10 #
1&
#1314
0&
#1316
b10 "
b10 !
b1 #
1&
#1318
0&
#1320
b1 "
b1 !
b10 #
1&
#1322
0&
#1324
b10 "
b10 !
b1 #
1&
#1326
0&
#1328
b1 "
b1 !
b10 #
1&
#1330
0&
#1332
b10 "
b10 !
b1 #
1&
#1334
0&
#1336
b1 "
b1 !
b10 #
1&
#1338
0&
#1340
b10 "
b10 !
b1 #
1&
#1342
0&
#1344
b1 "
b1 !
b10 #
1&
#1346
0&
#1347
b0 "
b0 !
b0 $
#1348
b0 #
1&
#1350
0&
#1352
1&
#1354
0&
#1356
1&
#1358
0&
#1360
1&
#1362
0&
#1364
1&
#1366
0&
#1368
1&
#1370
0&
#1372
1&
#1374
0&
#1376
1&
#1378
0&
#1380
1&
#1382
0&
#1384
1&
#1386
0&
#1388
1&
#1390
0&
#1392
1&
#1394
0&
#1395
b1 "
b1 !
b1 $
#1396
b0 "
b1 #
1&
#1398
0&
#1400
b1 "
b0 #
1&
#1402
0&
#1403
b11 "
b10 !
b11 $
#1404
b1 "
b1 !
b11 #
1&
#1406
0&
#1408
b10 "
b10 !
b1 #
1&
#1410
0&
#1412
b1 "
b1 !
b10 #
1&
#1414
0&
#1416
b10 "
b10 !
b1 #
1&
#1418
0&
#1420
b1 "
b1 !
b10 #
1&
#1422
0&
#1424
b10 "
b10 !
b1 #
1&
#1426
0&
#1428
b1 "
b1 !
b10 #
1&
#1430
0&
#1432
b10 "
b10 !
b1 #
1&
#1434
0&
#1436
b1 "
b1 !
b10 #
1&
#1438
0&
#1440
b10 "
b10 !
b1 #
1&
#1442
0&
#1443
b10 $
#1444
b10 #
1&
#1446
0&
#1448
1&
#1450
0&
#1452
1&
#1454
0&
#1456
1&
#1458
0&
#1459
b0 "
b0 !
b0 $
#1460
b0 #
1&
#1462
0&
#1464
1&
#1466
0&
#1468
1&
#1470
0&
#1472
1&
#1474
0&
#1476
1&
#1478
0&
#1480
1&
#1482
0&
#1484
1&
#1486
0&
#1488
1&
#1490
0&
#1491
b1 "
b1 !
b1 $
#1492
b0 "
b1 #
1&
#1494
0&
#1496
b1 "
b0 #
1&
#1498
0&
#1500
b0 "
b1 #
1&
#1502
0&
#1504
b1 "
b0 #
1&
#1506
0&
#1508
b0 "
b1 #
1&
#1510
0&
#1512
b1 "
b0 #
1&
#1514
0&
#1515
b11 "
b10 !
b11 $
#1516
b1 "
b1 !
b11 #
1&
#1518
0&
#1520
b10 "
b10 !
b1 #
1&
#1522
0&
#1524
b1 "
b1 !
b10 #
1&
#1526
0&
#1528
b10 "
b10 !
b1 #
1&
#1530
0&
#1532
b1 "
b1 !
b10 #
1&
#1534
0&
#1536
b10 "
b10 !
b1 #
1&
#1538
0&
#1539
b10 $
#1540
b10 #
1&
#1542
0&
#1544
1&
#1546
0&
#1548
1&
#1550
0&
#1552
1&
#1554
0&
#1556
1&
#1558
0&
#1560
1&
#1562
0&
#1564
1&
#1566
0&
#1568
1&
#1570
0&
#1571
b0 "
b0 !
b0 $
#1572
b0 #
1&
#1574
0&
#1576
1&
#1578
0&
#1580
1&
#1582
0&
#1584
1&
#1586
0&
#1587
b1 "
b1 !
b1 $
#1588
b0 "
b1 #
1&
#1590
0&
#1592
b1 "
b0 #
1&
#1594
0&
#1596
b0 "
b1 #
1&
#1598
0&
#1600
b1 "
b0 #
1&
#1602
0&
#1604
b0 "
b1 #
1&
#1606
0&
#1608
b1 "
b0 #
1&
#1610
0&
#1612
b0 "
b1 #
1&
#1614
0&
#1616
b1 "
b0 #
1&
#1618
0&
#1620
b0 "
b1 #
1&
#1622
0&
#1624
b1 "
b0 #
1&
#1626
0&
#1627
b11 "
b10 !
b11 $
#1628
b1 "
b1 !
b11 #
1&
#1630
0&
#1632
b10 "
b10 !
b1 #
1&
#1634
0&
#1635
b10 $
#1636
b10 #
1&
#1638
0&
#1640
1&
#1642
0&
#1644
1&
#1646
0&
#1648
1&
#1650
0&
#1652
1&
#1654
0&
#1656
1&
#1658
0&
#1660
1&
#1662
0&
#1664
1&
#1666
0&
#1668
1&
#1670
0&
#1672
1&
#1674
0&
#1676
1&
#1678
0&
#1680
1&
#1682
0&
#1683
b1 "
b1 !
b1 $
#1684
b0 "
b1 #
1&
#1686
0&
#1688
b1 "
b0 #
1&
#1690
0&
#1692
b0 "
b1 #
1&
#1694
0&
#1696
b1 "
b0 #
1&
#1698
0&
#1700
b0 "
b1 #
1&
#1702
0&
#1704
b1 "
b0 #
1&
#1706
0&
#1708
b0 "
b1 #
1&
#1710
0&
#1712
b1 "
b0 #
1&
#1714
0&
#1716
b0 "
b1 #
1&
#1718
0&
#1720
b1 "
b0 #
1&
#1722
0&
#1724
b0 "
b1 #
1&
#1726
0&
#1728
b1 "
b0 #
1&
#1730
0&
#1731
b0 "
b0 !
b0 $
#1732
1&
#1734
0&
#1736
1&
#1738
0&
#1739
b10 "
b10 !
b10 $
#1740
b10 #
1&
#1742
0&
#1744
1&
#1746
0&
#1748
1&
#1750
0&
#1752
1&
#1754
0&
#1756
1&
#1758
0&
#1760
1&
#1762
0&
#1764
1&
#1766
0&
#1768
1&
#1770
0&
#1772
1&
#1774
0&
#1776
1&
#1778
0&
#1779
b1 "
b1 !
b11 $
#1780
b10 "
b10 !
b1 #
1&
#1782
0&
#1784
b1 "
b1 !
b10 #
1&
#1786
0&
#1788
b10 "
b10 !
b1 #
1&
#1790
0&
#1792
b1 "
b1 !
b10 #
1&
#1794
0&
#1795
b1 $
#1796
b0 "
b1 #
1&
#1798
0&
#1800
b1 "
b0 #
1&
#1802
0&
#1804
b0 "
b1 #
1&
#1806
0&
#1808
b1 "
b0 #
1&
#1810
0&
#1812
b0 "
b1 #
1&
#1814
0&
#1816
b1 "
b0 #
1&
#1818
0&
#1820
b0 "
b1 #
1&
#1822
0&
#1824
b1 "
b0 #
1&
#1826
0&
#1827
b0 "
b0 !
b0 $
#1828
1&
#1830
0&
#1832
1&
#1834
0&
#1836
1&
#1838
0&
#1840
1&
#1842
0&
#1844
1&
#1846
0&
#1848
1&
#1850
0&
#1851
b10 "
b10 !
b10 $
#1852
b10 #
1&
#1854
0&
#1856
1&
#1858
0&
#1860
1&
#1862
0&
#1864
1&
#1866
0&
#1868
1&
#1870
0&
#1872
1&
#1874
0&
#1875
b1 "
b1 !
b11 $
#1876
b10 "
b10 !
b1 #
1&
#1878
0&
#1880
b1 "
b1 !
b10 #
1&
#1882
0&
#1884
b10 "
b10 !
b1 #
1&
#1886
0&
#1888
b1 "
b1 !
b10 #
1&
#1890
0&
#1892
b10 "
b10 !
b1 #
1&
#1894
0&
#1896
b1 "
b1 !
b10 #
1&
#1898
0&
#1900
b10 "
b10 !
b1 #
1&
#1902
0&
#1904
b1 "
b1 !
b10 #
1&
#1906
0&
#1907
b1 $
#1908
b0 "
b1 #
1&
#1910
0&
#1912
b1 "
b0 #
1&
#1914
0&
#1916
b0 "
b1 #
1&
#1918
0&
#1920
b1 "
b0 #
1&
#1922
0&
#1923
b0 "
b0 !
b0 $
#1924
1&
#1926
0&
#1928
1&
#1930
0&
#1932
1&
#1934
0&
#1936
1&
#1938
0&
#1940
1&
#1942
0&
#1944
1&
#1946
0&
#1948
1&
#1950
0&
#1952
1&
#1954
0&
#1956
1&
#1958
0&
#1960
1&
#1962
0&
#1963
b10 "
b10 !
b10 $
#1964
b10 #
1&
#1966
0&
#1968
1&
#1970
0&
#1971
b1 "
b1 !
b11 $
#1972
b10 "
b10 !
b1 #
1&
#1974
0&
#1976
b1 "
b1 !
b10 #
1&
#1978
0&
#1980
b10 "
b10 !
b1 #
1&
#1982
0&
#1984
b1 "
b1 !
b10 #
1&
#1986
0&
#1988
b10 "
b10 !
b1 #
1&
#1990
0&
#1992
b1 "
b1 !
b10 #
1&
#1994
0&
#1996
b10 "
b10 !
b1 #
1&
#1998
0&
#2000
b1 "
b1 !
b10 #
1&
#2002
0&
#2004
b10 "
b10 !
b1 #
1&
#2006
0&
#2008
b1 "
b1 !
b10 #
1&
#2010
0&
#2012
b10 "
b10 !
b1 #
1&
#2014
0&
#2016
b1 "
b1 !
b10 #
1&
#2018
0&
#2019
b0 "
b0 !
b0 $
#2020
b0 #
1&
#2022
0&
#2024
1&
#2026
0&
#2028
1&
#2030
0&
#2032
1&
#2034
0&
#2036
1&
#2038
0&
#2040
1&
#2042
0&
#2044
1&
#2046
0&
#2048
1&
#2050
0&
#2052
1&
#2054
0&
#2056
1&
#2058
0&
#2060
1&
#2062
0&
#2064
1&
#2066
0&
#2067
b1 "
b1 !
b1 $
#2068
b0 "
b1 #
1&
#2070
0&
#2072
b1 "
b0 #
1&
#2074
0&
#2075
b11 "
b10 !
b11 $
#2076
b1 "
b1 !
b11 #
1&
#2078
0&
#2080
b10 "
b10 !
b1 #
1&
#2082
0&
#2084
b1 "
b1 !
b10 #
1&
#2086
0&
#2088
b10 "
b10 !
b1 #
1&
#2090
0&
#2092
b1 "
b1 !
b10 #
1&
#2094
0&
#2096
b10 "
b10 !
b1 #
1&
#2098
0&
#2100
b1 "
b1 !
b10 #
1&
#2102
0&
#2104
b10 "
b10 !
b1 #
1&
#2106
0&
#2108
b1 "
b1 !
b10 #
1&
#2110
0&
#2112
b10 "
b10 !
b1 #
1&
#2114
0&
#2115
b10 $
#2116
b10 #
1&
#2118
0&
#2120
1&
#2122
0&
#2124
1&
#2126
0&
#2128
1&
#2130
0&
#2131
b0 "
b0 !
b0 $
#2132
b0 #
1&
#2134
0&
#2136
1&
#2138
0&
#2140
1&
#2142
0&
#2144
1&
#2146
0&
#2148
1&
#2150
0&
#2152
1&
#2154
0&
#2156
1&
#2158
0&
#2160
1&
#2162
0&
#2163
b1 "
b1 !
b1 $
#2164
b0 "
b1 #
1&
#2166
0&
#2168
b1 "
b0 #
1&
#2170
0&
#2172
b0 "
b1 #
1&
#2174
0&
#2176
b1 "
b0 #
1&
#2178
0&
#2180
b0 "
b1 #
1&
#2182
0&
#2184
b1 "
b0 #
1&
#2186
0&
#2187
b11 "
b10 !
b11 $
#2188
b1 "
b1 !
b11 #
1&
#2190
0&
#2192
b10 "
b10 !
b1 #
1&
#2194
0&
#2196
b1 "
b1 !
b10 #
1&
#2198
0&
#2200
b10 "
b10 !
b1 #
1&
#2202
0&
#2204
b1 "
b1 !
b10 #
1&
#2206
0&
#2208
b10 "
b10 !
b1 #
1&
#2210
0&
#2211
b10 $
#2212
b10 #
1&
#2214
0&
#2216
1&
#2218
0&
#2220
1&
#2222
0&
#2224
1&
#2226
0&
#2228
1&
#2230
0&
#2232
1&
#2234
0&
#2236
1&
#2238
0&
#2240
1&
#2242
0&
#2243
b0 "
b0 !
b0 $
#2244
b0 #
1&
#2246
0&
#2248
1&
#2250
0&
#2252
1&
#2254
0&
#2256
1&
#2258
0&
#2259
b1 "
b1 !
b1 $
#2260
b0 "
b1 #
1&
#2262
0&
#2264
b1 "
b0 #
1&
#2266
0&
#2268
b0 "
b1 #
1&
#2270
0&
#2272
b1 "
b0 #
1&
#2274
0&
#2276
b0 "
b1 #
1&
#2278
0&
#2280
b1 "
b0 #
1&
#2282
0&
#2284
b0 "
b1 #
1&
#2286
0&
#2288
b1 "
b0 #
1&
#2290
0&
#2292
b0 "
b1 #
1&
#2294
0&
#2296
b1 "
b0 #
1&
#2298
0&
#2299
b11 "
b10 !
b11 $
#2300
b1 "
b1 !
b11 #
1&
#2302
0&
#2304
b10 "
b10 !
b1 #
1&
#2306
0&
#2307
b10 $
#2308
b10 #
1&
#2310
0&
#2312
1&
#2314
0&
#2316
1&
#2318
0&
#2320
1&
#2322
0&
#2324
1&
#2326
0&
#2328
1&
#2330
0&
#2332
1&
#2334
0&
#2336
1&
#2338
0&
#2340
1&
#2342
0&
#2344
1&
#2346
0&
#2348
1&
#2350
0&
#2352
1&
#2354
0&
#2355
b1 "
b1 !
b1 $
#2356
b0 "
b1 #
1&
#2358
0&
#2360
b1 "
b0 #
1&
#2362
0&
#2364
b0 "
b1 #
1&
#2366
0&
#2368
b1 "
b0 #
1&
#2370
0&
#2372
b0 "
b1 #
1&
#2374
0&
#2376
b1 "
b0 #
1&
#2378
0&
#2380
b0 "
b1 #
1&
#2382
0&
#2384
b1 "
b0 #
1&
#2386
0&
#2388
b0 "
b1 #
1&
#2390
0&
#2392
b1 "
b0 #
1&
#2394
0&
#2396
b0 "
b1 #
1&
#2398
0&
#2400
b1 "
b0 #
1&
#2402
0&
#2403
b0 "
b0 !
b0 $
#2404
1&
#2406
0&
#2408
1&
#2410
0&
#2411
b10 "
b10 !
b10 $
#2412
b10 #
1&
#2414
0&
#2416
1&
#2418
0&
#2420
1&
#2422
0&
#2424
1&
#2426
0&
#2428
1&
#2430
0&
#2432
1&
#2434
0&
#2436
1&
#2438
0&
#2440
1&
#2442
0&
#2444
1&
#2446
0&
#2448
1&
#2450
0&
#2451
b1 "
b1 !
b11 $
#2452
b10 "
b10 !
b1 #
1&
#2454
0&
#2456
b1 "
b1 !
b10 #
1&
#2458
0&
#2460
b10 "
b10 !
b1 #
1&
#2462
0&
#2464
b1 "
b1 !
b10 #
1&
#2466
0&
#2467
b1 $
#2468
b0 "
b1 #
1&
#2470
0&
#2472
b1 "
b0 #
1&
#2474
0&
#2476
b0 "
b1 #
1&
#2478
0&
#2480
b1 "
b0 #
1&
#2482
0&
#2484
b0 "
b1 #
1&
#2486
0&
#2488
b1 "
b0 #
1&
#2490
0&
#2492
b0 "
b1 #
1&
#2494
0&
#2496
b1 "
b0 #
1&
#2498
0&
#2499
b0 "
b0 !
b0 $
#2500
1&
#2502
0&
#2504
1&
#2506
0&
#2508
1&
#2510
0&
#2512
1&
#2514
0&
#2516
1&
#2518
0&
#2520
1&
#2522
0&
#2523
b10 "
b10 !
b10 $
#2524
b10 #
1&
#2526
0&
#2528
1&
#2530
0&
#2532
1&
#2534
0&
#2536
1&
#2538
0&
#2540
1&
#2542
0&
#2544
1&
#2546
0&
#2547
b1 "
b1 !
b11 $
#2548
b10 "
b10 !
b1 #
1&
#2550
0&
#2552
b1 "
b1 !
b10 #
1&
#2554
0&
#2556
b10 "
b10 !
b1 #
1&
#2558
0&
#2560
b1 "
b1 !
b10 #
1&
#2562
0&
