BS/cmpe240 lab/Lab2/Lab2finished/destiny.v
module destiny(y, i2, i1, i0);
  input i0, i1, i2;
  output y;

  wire i0_not;
  wire i1_not;
  wire i1_and_i2;

  wire y;

  not(i0_not, i0);
  not(i1_not, i1);
  and(i1_and_i2, i1_not, i2);
  or(y, i0_not, i1_and_i2);

endmodule

cmpe240 lab/Lab2/Lab2finished/testbench_gate.v
`timescale 1ns / 1ns
module TestBench();

reg x2, x1, x0;
wire y;

destiny my_module(y, x2, x1, x0);

initial begin
	$dumpfile("TimingDiagram.vcd");
	$dumpvars(0, y, x2, x1, x0);

	x2 = 0; x1 = 0; x0 = 0;
	#20
	x2 = 0; x1 = 0; x0 = 1;
	#20
	x2 = 0; x1 = 1; x0 = 0;
	#20
	x2 = 0; x1 = 1; x0 = 1;
	#20
	x2 = 1; x1 = 0; x0 = 0;
	#20
	x2 = 1; x1 = 0; x0 = 1;
	#20
	x2 = 1; x1 = 1; x0 = 0;
	#20
	x2 = 1; x1 = 1; x0 = 1;
	#20
	$finish;
end

endmodule

BS/cmpe240 lab/Lab2/Lab2finished/TimingDiagram.vcd
$date
	Thu Feb 22 22:26:24 2018
$end
$version
	Icarus Verilog
$end
$timescale
	1ns
$end
$scope module TestBench $end
$var wire 1 ! y $end
$upscope $end
$scope module TestBench $end
$var reg 1 " x2 $end
$upscope $end
$scope module TestBench $end
$var reg 1 # x1 $end
$upscope $end
$scope module TestBench $end
$var reg 1 $ x0 $end
$upscope $end
$enddefinitions $end
#0
$dumpvars
0$
0#
0"
1!
$end
#20
0!
1$
#40
1!
0$
1#
#60
0!
1$
#80
1!
0$
0#
1"
#100
1$
#120
0$
1#
#140
0!
1$
