BS/cmpe240 lab/Lab6/mymodule.v
`timescale 1ns/1ns
module mymodule(X, Y, S, zero, negative, Overflow, Cout, F);

input [4:0] Y;
input [4:0] X;
input [1:0] S;

output reg Cout;
output reg zero;
output reg Overflow;
output reg negative;
output reg [4:0] F;
		
always @(X, Y, S) begin
	case(S)
    2'b00: begin
		Overflow = 0;
        Cout = X != Y;
        negative = 0;
        F = 0;
        if(F == 0) zero = 1;
        else zero = 0;

	end
	2'b01: begin
		Overflow = 0;
        negative = 0;
        {Cout, F} = X[4:2] * Y[3:1];
        if(F == 0) zero = 1;
        else zero = 0;
	end
	2'b10: begin
		{Cout, F} = X + {Y[3],Y[2],Y[1]};
        negative = F[4];
        Overflow = ~X[4] & F[4];
        if(F == 0) zero = 1;
        else zero = 0;
	end
	2'b11: begin
    
		{Cout, F} = X + Y + 5'b00001;
		
        Overflow = ~X[4] & ~Y[4] & F[4] | X[4] & Y[4] & ~F[4];

        if(F == 0) zero = 1;
        else zero = 0;

        negative = F[4];
	end
    endcase
end
endmodule

BS/cmpe240 lab/Lab6/test_bench.v
`timescale 1ns/1ns
module testbench();

  reg [4:0] X;
  reg [4:0] Y;
  reg [1:0] S;

     wire Cout;
    wire zero;
     wire Overflow;
     wire negative;
     wire [4:0] F;

  mymodule asd(X, Y, S, zero, negative, Overflow, Cout, F);

  initial begin
    $dumpfile("TimingDiagram.vcd");
    $dumpvars(0, X, Y, S, zero, negative, Overflow, Cout, F);

    S <= 2'b00;
    X <= 5'b00000;
    Y <= 5'b00000;

    #20
    repeat(4) begin
        repeat(32) begin
            repeat(32) begin

                #2;
                Y <= Y + 1;

            end
            X <= X + 1;
        end 
                S <= S + 1; 

        end
    $finish;
  end
endmodule

cmpe240 lab/Lab6/TimingDiagram.vcd
$date
	Wed May 16 12:05:06 2018
$end
$version
	Icarus Verilog
$end
$timescale
	1ns
$end
$scope module testbench $end
$var reg 5 ! X [4:0] $end
$upscope $end
$scope module testbench $end
$var reg 5 " Y [4:0] $end
$upscope $end
$scope module testbench $end
$var reg 2 # S [1:0] $end
$upscope $end
$scope module testbench $end
$var wire 1 $ zero $end
$upscope $end
$scope module testbench $end
$var wire 1 % negative $end
$upscope $end
$scope module testbench $end
$var wire 1 & Overflow $end
$upscope $end
$scope module testbench $end
$var wire 1 ' Cout $end
$upscope $end
$scope module testbench $end
$var wire 5 ( F [4:0] $end
$upscope $end
$enddefinitions $end
#0
$dumpvars
b0 (
0'
0&
0%
1$
b0 #
b0 "
b0 !
$end
#22
1'
b1 "
#24
b10 "
#26
b11 "
#28
b100 "
#30
b101 "
#32
b110 "
#34
b111 "
#36
b1000 "
#38
b1001 "
#40
b1010 "
#42
b1011 "
#44
b1100 "
#46
b1101 "
#48
b1110 "
#50
b1111 "
#52
b10000 "
#54
b10001 "
#56
b10010 "
#58
b10011 "
#60
b10100 "
#62
b10101 "
#64
b10110 "
#66
b10111 "
#68
b11000 "
#70
b11001 "
#72
b11010 "
#74
b11011 "
#76
b11100 "
#78
b11101 "
#80
b11110 "
#82
b11111 "
#84
b1 !
b0 "
#86
0'
b1 "
#88
1'
b10 "
#90
b11 "
#92
b100 "
#94
b101 "
#96
b110 "
#98
b111 "
#100
b1000 "
#102
b1001 "
#104
b1010 "
#106
b1011 "
#108
b1100 "
#110
b1101 "
#112
b1110 "
#114
b1111 "
#116
b10000 "
#118
b10001 "
#120
b10010 "
#122
b10011 "
#124
b10100 "
#126
b10101 "
#128
b10110 "
#130
b10111 "
#132
b11000 "
#134
b11001 "
#136
b11010 "
#138
b11011 "
#140
b11100 "
#142
b11101 "
#144
b11110 "
#146
b11111 "
#148
b10 !
b0 "
#150
b1 "
#152
0'
b10 "
#154
1'
b11 "
#156
b100 "
#158
b101 "
#160
b110 "
#162
b111 "
#164
b1000 "
#166
b1001 "
#168
b1010 "
#170
b1011 "
#172
b1100 "
#174
b1101 "
#176
b1110 "
#178
b1111 "
#180
b10000 "
#182
b10001 "
#184
b10010 "
#186
b10011 "
#188
b10100 "
#190
b10101 "
#192
b10110 "
#194
b10111 "
#196
b11000 "
#198
b11001 "
#200
b11010 "
#202
b11011 "
#204
b11100 "
#206
b11101 "
#208
b11110 "
#210
b11111 "
#212
b11 !
b0 "
#214
b1 "
#216
b10 "
#218
0'
b11 "
#220
1'
b100 "
#222
b101 "
#224
b110 "
#226
b111 "
#228
b1000 "
#230
b1001 "
#232
b1010 "
#234
b1011 "
#236
b1100 "
#238
b1101 "
#240
b1110 "
#242
b1111 "
#244
b10000 "
#246
b10001 "
#248
b10010 "
#250
b10011 "
#252
b10100 "
#254
b10101 "
#256
b10110 "
#258
b10111 "
#260
b11000 "
#262
b11001 "
#264
b11010 "
#266
b11011 "
#268
b11100 "
#270
b11101 "
#272
b11110 "
#274
b11111 "
#276
b100 !
b0 "
#278
b1 "
#280
b10 "
#282
b11 "
#284
0'
b100 "
#286
1'
b101 "
#288
b110 "
#290
b111 "
#292
b1000 "
#294
b1001 "
#296
b1010 "
#298
b1011 "
#300
b1100 "
#302
b1101 "
#304
b1110 "
#306
b1111 "
#308
b10000 "
#310
b10001 "
#312
b10010 "
#314
b10011 "
#316
b10100 "
#318
b10101 "
#320
b10110 "
#322
b10111 "
#324
b11000 "
#326
b11001 "
#328
b11010 "
#330
b11011 "
#332
b11100 "
#334
b11101 "
#336
b11110 "
#338
b11111 "
#340
b101 !
b0 "
#342
b1 "
#344
b10 "
#346
b11 "
#348
b100 "
#350
0'
b101 "
#352
1'
b110 "
#354
b111 "
#356
b1000 "
#358
b1001 "
#360
b1010 "
#362
b1011 "
#364
b1100 "
#366
b1101 "
#368
b1110 "
#370
b1111 "
#372
b10000 "
#374
b10001 "
#376
b10010 "
#378
b10011 "
#380
b10100 "
#382
b10101 "
#384
b10110 "
#386
b10111 "
#388
b11000 "
#390
b11001 "
#392
b11010 "
#394
b11011 "
#396
b11100 "
#398
b11101 "
#400
b11110 "
#402
b11111 "
#404
b110 !
b0 "
#406
b1 "
#408
b10 "
#410
b11 "
#412
b100 "
#414
b101 "
#416
0'
b110 "
#418
1'
b111 "
#420
b1000 "
#422
b1001 "
#424
b1010 "
#426
b1011 "
#428
b1100 "
#430
b1101 "
#432
b1110 "
#434
b1111 "
#436
b10000 "
#438
b10001 "
#440
b10010 "
#442
b10011 "
#444
b10100 "
#446
b10101 "
#448
b10110 "
#450
b10111 "
#452
b11000 "
#454
b11001 "
#456
b11010 "
#458
b11011 "
#460
b11100 "
#462
b11101 "
#464
b11110 "
#466
b11111 "
#468
b111 !
b0 "
#470
b1 "
#472
b10 "
#474
b11 "
#476
b100 "
#478
b101 "
#480
b110 "
#482
0'
b111 "
#484
1'
b1000 "
#486
b1001 "
#488
b1010 "
#490
b1011 "
#492
b1100 "
#494
b1101 "
#496
b1110 "
#498
b1111 "
#500
b10000 "
#502
b10001 "
#504
b10010 "
#506
b10011 "
#508
b10100 "
#510
b10101 "
#512
b10110 "
#514
b10111 "
#516
b11000 "
#518
b11001 "
#520
b11010 "
#522
b11011 "
#524
b11100 "
#526
b11101 "
#528
b11110 "
#530
b11111 "
#532
b1000 !
b0 "
#534
b1 "
#536
b10 "
#538
b11 "
#540
b100 "
#542
b101 "
#544
b110 "
#546
b111 "
#548
0'
b1000 "
#550
1'
b1001 "
#552
b1010 "
#554
b1011 "
#556
b1100 "
#558
b1101 "
#560
b1110 "
#562
b1111 "
#564
b10000 "
#566
b10001 "
#568
b10010 "
#570
b10011 "
#572
b10100 "
#574
b10101 "
#576
b10110 "
#578
b10111 "
#580
b11000 "
#582
b11001 "
#584
b11010 "
#586
b11011 "
#588
b11100 "
#590
b11101 "
#592
b11110 "
#594
b11111 "
#596
b1001 !
b0 "
#598
b1 "
#600
b10 "
#602
b11 "
#604
b100 "
#606
b101 "
#608
b110 "
#610
b111 "
#612
b1000 "
#614
0'
b1001 "
#616
1'
b1010 "
#618
b1011 "
#620
b1100 "
#622
b1101 "
#624
b1110 "
#626
b1111 "
#628
b10000 "
#630
b10001 "
#632
b10010 "
#634
b10011 "
#636
b10100 "
#638
b10101 "
#640
b10110 "
#642
b10111 "
#644
b11000 "
#646
b11001 "
#648
b11010 "
#650
b11011 "
#652
b11100 "
#654
b11101 "
#656
b11110 "
#658
b11111 "
#660
b1010 !
b0 "
#662
b1 "
#664
b10 "
#666
b11 "
#668
b100 "
#670
b101 "
#672
b110 "
#674
b111 "
#676
b1000 "
#678
b1001 "
#680
0'
b1010 "
#682
1'
b1011 "
#684
b1100 "
#686
b1101 "
#688
b1110 "
#690
b1111 "
#692
b10000 "
#694
b10001 "
#696
b10010 "
#698
b10011 "
#700
b10100 "
#702
b10101 "
#704
b10110 "
#706
b10111 "
#708
b11000 "
#710
b11001 "
#712
b11010 "
#714
b11011 "
#716
b11100 "
#718
b11101 "
#720
b11110 "
#722
b11111 "
#724
b1011 !
b0 "
#726
b1 "
#728
b10 "
#730
b11 "
#732
b100 "
#734
b101 "
#736
b110 "
#738
b111 "
#740
b1000 "
#742
b1001 "
#744
b1010 "
#746
0'
b1011 "
#748
1'
b1100 "
#750
b1101 "
#752
b1110 "
#754
b1111 "
#756
b10000 "
#758
b10001 "
#760
b10010 "
#762
b10011 "
#764
b10100 "
#766
b10101 "
#768
b10110 "
#770
b10111 "
#772
b11000 "
#774
b11001 "
#776
b11010 "
#778
b11011 "
#780
b11100 "
#782
b11101 "
#784
b11110 "
#786
b11111 "
#788
b1100 !
b0 "
#790
b1 "
#792
b10 "
#794
b11 "
#796
b100 "
#798
b101 "
#800
b110 "
#802
b111 "
#804
b1000 "
#806
b1001 "
#808
b1010 "
#810
b1011 "
#812
0'
b1100 "
#814
1'
b1101 "
#816
b1110 "
#818
b1111 "
#820
b10000 "
#822
b10001 "
#824
b10010 "
#826
b10011 "
#828
b10100 "
#830
b10101 "
#832
b10110 "
#834
b10111 "
#836
b11000 "
#838
b11001 "
#840
b11010 "
#842
b11011 "
#844
b11100 "
#846
b11101 "
#848
b11110 "
#850
b11111 "
#852
b1101 !
b0 "
#854
b1 "
#856
b10 "
#858
b11 "
#860
b100 "
#862
b101 "
#864
b110 "
#866
b111 "
#868
b1000 "
#870
b1001 "
#872
b1010 "
#874
b1011 "
#876
b1100 "
#878
0'
b1101 "
#880
1'
b1110 "
#882
b1111 "
#884
b10000 "
#886
b10001 "
#888
b10010 "
#890
b10011 "
#892
b10100 "
#894
b10101 "
#896
b10110 "
#898
b10111 "
#900
b11000 "
#902
b11001 "
#904
b11010 "
#906
b11011 "
#908
b11100 "
#910
b11101 "
#912
b11110 "
#914
b11111 "
#916
b1110 !
b0 "
#918
b1 "
#920
b10 "
#922
b11 "
#924
b100 "
#926
b101 "
#928
b110 "
#930
b111 "
#932
b1000 "
#934
b1001 "
#936
b1010 "
#938
b1011 "
#940
b1100 "
#942
b1101 "
#944
0'
b1110 "
#946
1'
b1111 "
#948
b10000 "
#950
b10001 "
#952
b10010 "
#954
b10011 "
#956
b10100 "
#958
b10101 "
#960
b10110 "
#962
b10111 "
#964
b11000 "
#966
b11001 "
#968
b11010 "
#970
b11011 "
#972
b11100 "
#974
b11101 "
#976
b11110 "
#978
b11111 "
#980
b1111 !
b0 "
#982
b1 "
#984
b10 "
#986
b11 "
#988
b100 "
#990
b101 "
#992
b110 "
#994
b111 "
#996
b1000 "
#998
b1001 "
#1000
b1010 "
#1002
b1011 "
#1004
b1100 "
#1006
b1101 "
#1008
b1110 "
#1010
0'
b1111 "
#1012
1'
b10000 "
#1014
b10001 "
#1016
b10010 "
#1018
b10011 "
#1020
b10100 "
#1022
b10101 "
#1024
b10110 "
#1026
b10111 "
#1028
b11000 "
#1030
b11001 "
#1032
b11010 "
#1034
b11011 "
#1036
b11100 "
#1038
b11101 "
#1040
b11110 "
#1042
b11111 "
#1044
b10000 !
b0 "
#1046
b1 "
#1048
b10 "
#1050
b11 "
#1052
b100 "
#1054
b101 "
#1056
b110 "
#1058
b111 "
#1060
b1000 "
#1062
b1001 "
#1064
b1010 "
#1066
b1011 "
#1068
b1100 "
#1070
b1101 "
#1072
b1110 "
#1074
b1111 "
#1076
0'
b10000 "
#1078
1'
b10001 "
#1080
b10010 "
#1082
b10011 "
#1084
b10100 "
#1086
b10101 "
#1088
b10110 "
#1090
b10111 "
#1092
b11000 "
#1094
b11001 "
#1096
b11010 "
#1098
b11011 "
#1100
b11100 "
#1102
b11101 "
#1104
b11110 "
#1106
b11111 "
#1108
b10001 !
b0 "
#1110
b1 "
#1112
b10 "
#1114
b11 "
#1116
b100 "
#1118
b101 "
#1120
b110 "
#1122
b111 "
#1124
b1000 "
#1126
b1001 "
#1128
b1010 "
#1130
b1011 "
#1132
b1100 "
#1134
b1101 "
#1136
b1110 "
#1138
b1111 "
#1140
b10000 "
#1142
0'
b10001 "
#1144
1'
b10010 "
#1146
b10011 "
#1148
b10100 "
#1150
b10101 "
#1152
b10110 "
#1154
b10111 "
#1156
b11000 "
#1158
b11001 "
#1160
b11010 "
#1162
b11011 "
#1164
b11100 "
#1166
b11101 "
#1168
b11110 "
#1170
b11111 "
#1172
b10010 !
b0 "
#1174
b1 "
#1176
b10 "
#1178
b11 "
#1180
b100 "
#1182
b101 "
#1184
b110 "
#1186
b111 "
#1188
b1000 "
#1190
b1001 "
#1192
b1010 "
#1194
b1011 "
#1196
b1100 "
#1198
b1101 "
#1200
b1110 "
#1202
b1111 "
#1204
b10000 "
#1206
b10001 "
#1208
0'
b10010 "
#1210
1'
b10011 "
#1212
b10100 "
#1214
b10101 "
#1216
b10110 "
#1218
b10111 "
#1220
b11000 "
#1222
b11001 "
#1224
b11010 "
#1226
b11011 "
#1228
b11100 "
#1230
b11101 "
#1232
b11110 "
#1234
b11111 "
#1236
b10011 !
b0 "
#1238
b1 "
#1240
b10 "
#1242
b11 "
#1244
b100 "
#1246
b101 "
#1248
b110 "
#1250
b111 "
#1252
b1000 "
#1254
b1001 "
#1256
b1010 "
#1258
b1011 "
#1260
b1100 "
#1262
b1101 "
#1264
b1110 "
#1266
b1111 "
#1268
b10000 "
#1270
b10001 "
#1272
b10010 "
#1274
0'
b10011 "
#1276
1'
b10100 "
#1278
b10101 "
#1280
b10110 "
#1282
b10111 "
#1284
b11000 "
#1286
b11001 "
#1288
b11010 "
#1290
b11011 "
#1292
b11100 "
#1294
b11101 "
#1296
b11110 "
#1298
b11111 "
#1300
b10100 !
b0 "
#1302
b1 "
#1304
b10 "
#1306
b11 "
#1308
b100 "
#1310
b101 "
#1312
b110 "
#1314
b111 "
#1316
b1000 "
#1318
b1001 "
#1320
b1010 "
#1322
b1011 "
#1324
b1100 "
#1326
b1101 "
#1328
b1110 "
#1330
b1111 "
#1332
b10000 "
#1334
b10001 "
#1336
b10010 "
#1338
b10011 "
#1340
0'
b10100 "
#1342
1'
b10101 "
#1344
b10110 "
#1346
b10111 "
#1348
b11000 "
#1350
b11001 "
#1352
b11010 "
#1354
b11011 "
#1356
b11100 "
#1358
b11101 "
#1360
b11110 "
#1362
b11111 "
#1364
b10101 !
b0 "
#1366
b1 "
#1368
b10 "
#1370
b11 "
#1372
b100 "
#1374
b101 "
#1376
b110 "
#1378
b111 "
#1380
b1000 "
#1382
b1001 "
#1384
b1010 "
#1386
b1011 "
#1388
b1100 "
#1390
b1101 "
#1392
b1110 "
#1394
b1111 "
#1396
b10000 "
#1398
b10001 "
#1400
b10010 "
#1402
b10011 "
#1404
b10100 "
#1406
0'
b10101 "
#1408
1'
b10110 "
#1410
b10111 "
#1412
b11000 "
#1414
b11001 "
#1416
b11010 "
#1418
b11011 "
#1420
b11100 "
#1422
b11101 "
#1424
b11110 "
#1426
b11111 "
#1428
b10110 !
b0 "
#1430
b1 "
#1432
b10 "
#1434
b11 "
#1436
b100 "
#1438
b101 "
#1440
b110 "
#1442
b111 "
#1444
b1000 "
#1446
b1001 "
#1448
b1010 "
#1450
b1011 "
#1452
b1100 "
#1454
b1101 "
#1456
b1110 "
#1458
b1111 "
#1460
b10000 "
#1462
b10001 "
#1464
b10010 "
#1466
b10011 "
#1468
b10100 "
#1470
b10101 "
#1472
0'
b10110 "
#1474
1'
b10111 "
#1476
b11000 "
#1478
b11001 "
#1480
b11010 "
#1482
b11011 "
#1484
b11100 "
#1486
b11101 "
#1488
b11110 "
#1490
b11111 "
#1492
b10111 !
b0 "
#1494
b1 "
#1496
b10 "
#1498
b11 "
#1500
b100 "
#1502
b101 "
#1504
b110 "
#1506
b111 "
#1508
b1000 "
#1510
b1001 "
#1512
b1010 "
#1514
b1011 "
#1516
b1100 "
#1518
b1101 "
#1520
b1110 "
#1522
b1111 "
#1524
b10000 "
#1526
b10001 "
#1528
b10010 "
#1530
b10011 "
#1532
b10100 "
#1534
b10101 "
#1536
b10110 "
#1538
0'
b10111 "
#1540
1'
b11000 "
#1542
b11001 "
#1544
b11010 "
#1546
b11011 "
#1548
b11100 "
#1550
b11101 "
#1552
b11110 "
#1554
b11111 "
#1556
b11000 !
b0 "
#1558
b1 "
#1560
b10 "
#1562
b11 "
#1564
b100 "
#1566
b101 "
#1568
b110 "
#1570
b111 "
#1572
b1000 "
#1574
b1001 "
#1576
b1010 "
#1578
b1011 "
#1580
b1100 "
#1582
b1101 "
#1584
b1110 "
#1586
b1111 "
#1588
b10000 "
#1590
b10001 "
#1592
b10010 "
#1594
b10011 "
#1596
b10100 "
#1598
b10101 "
#1600
b10110 "
#1602
b10111 "
#1604
0'
b11000 "
#1606
1'
b11001 "
#1608
b11010 "
#1610
b11011 "
#1612
b11100 "
#1614
b11101 "
#1616
b11110 "
#1618
b11111 "
#1620
b11001 !
b0 "
#1622
b1 "
#1624
b10 "
#1626
b11 "
#1628
b100 "
#1630
b101 "
#1632
b110 "
#1634
b111 "
#1636
b1000 "
#1638
b1001 "
#1640
b1010 "
#1642
b1011 "
#1644
b1100 "
#1646
b1101 "
#1648
b1110 "
#1650
b1111 "
#1652
b10000 "
#1654
b10001 "
#1656
b10010 "
#1658
b10011 "
#1660
b10100 "
#1662
b10101 "
#1664
b10110 "
#1666
b10111 "
#1668
b11000 "
#1670
0'
b11001 "
#1672
1'
b11010 "
#1674
b11011 "
#1676
b11100 "
#1678
b11101 "
#1680
b11110 "
#1682
b11111 "
#1684
b11010 !
b0 "
#1686
b1 "
#1688
b10 "
#1690
b11 "
#1692
b100 "
#1694
b101 "
#1696
b110 "
#1698
b111 "
#1700
b1000 "
#1702
b1001 "
#1704
b1010 "
#1706
b1011 "
#1708
b1100 "
#1710
b1101 "
#1712
b1110 "
#1714
b1111 "
#1716
b10000 "
#1718
b10001 "
#1720
b10010 "
#1722
b10011 "
#1724
b10100 "
#1726
b10101 "
#1728
b10110 "
#1730
b10111 "
#1732
b11000 "
#1734
b11001 "
#1736
0'
b11010 "
#1738
1'
b11011 "
#1740
b11100 "
#1742
b11101 "
#1744
b11110 "
#1746
b11111 "
#1748
b11011 !
b0 "
#1750
b1 "
#1752
b10 "
#1754
b11 "
#1756
b100 "
#1758
b101 "
#1760
b110 "
#1762
b111 "
#1764
b1000 "
#1766
b1001 "
#1768
b1010 "
#1770
b1011 "
#1772
b1100 "
#1774
b1101 "
#1776
b1110 "
#1778
b1111 "
#1780
b10000 "
#1782
b10001 "
#1784
b10010 "
#1786
b10011 "
#1788
b10100 "
#1790
b10101 "
#1792
b10110 "
#1794
b10111 "
#1796
b11000 "
#1798
b11001 "
#1800
b11010 "
#1802
0'
b11011 "
#1804
1'
b11100 "
#1806
b11101 "
#1808
b11110 "
#1810
b11111 "
#1812
b11100 !
b0 "
#1814
b1 "
#1816
b10 "
#1818
b11 "
#1820
b100 "
#1822
b101 "
#1824
b110 "
#1826
b111 "
#1828
b1000 "
#1830
b1001 "
#1832
b1010 "
#1834
b1011 "
#1836
b1100 "
#1838
b1101 "
#1840
b1110 "
#1842
b1111 "
#1844
b10000 "
#1846
b10001 "
#1848
b10010 "
#1850
b10011 "
#1852
b10100 "
#1854
b10101 "
#1856
b10110 "
#1858
b10111 "
#1860
b11000 "
#1862
b11001 "
#1864
b11010 "
#1866
b11011 "
#1868
0'
b11100 "
#1870
1'
b11101 "
#1872
b11110 "
#1874
b11111 "
#1876
b11101 !
b0 "
#1878
b1 "
#1880
b10 "
#1882
b11 "
#1884
b100 "
#1886
b101 "
#1888
b110 "
#1890
b111 "
#1892
b1000 "
#1894
b1001 "
#1896
b1010 "
#1898
b1011 "
#1900
b1100 "
#1902
b1101 "
#1904
b1110 "
#1906
b1111 "
#1908
b10000 "
#1910
b10001 "
#1912
b10010 "
#1914
b10011 "
#1916
b10100 "
#1918
b10101 "
#1920
b10110 "
#1922
b10111 "
#1924
b11000 "
#1926
b11001 "
#1928
b11010 "
#1930
b11011 "
#1932
b11100 "
#1934
0'
b11101 "
#1936
1'
b11110 "
#1938
b11111 "
#1940
b11110 !
b0 "
#1942
b1 "
#1944
b10 "
#1946
b11 "
#1948
b100 "
#1950
b101 "
#1952
b110 "
#1954
b111 "
#1956
b1000 "
#1958
b1001 "
#1960
b1010 "
#1962
b1011 "
#1964
b1100 "
#1966
b1101 "
#1968
b1110 "
#1970
b1111 "
#1972
b10000 "
#1974
b10001 "
#1976
b10010 "
#1978
b10011 "
#1980
b10100 "
#1982
b10101 "
#1984
b10110 "
#1986
b10111 "
#1988
b11000 "
#1990
b11001 "
#1992
b11010 "
#1994
b11011 "
#1996
b11100 "
#1998
b11101 "
#2000
0'
b11110 "
#2002
1'
b11111 "
#2004
b11111 !
b0 "
#2006
b1 "
#2008
b10 "
#2010
b11 "
#2012
b100 "
#2014
b101 "
#2016
b110 "
#2018
b111 "
#2020
b1000 "
#2022
b1001 "
#2024
b1010 "
#2026
b1011 "
#2028
b1100 "
#2030
b1101 "
#2032
b1110 "
#2034
b1111 "
#2036
b10000 "
#2038
b10001 "
#2040
b10010 "
#2042
b10011 "
#2044
b10100 "
#2046
b10101 "
#2048
b10110 "
#2050
b10111 "
#2052
b11000 "
#2054
b11001 "
#2056
b11010 "
#2058
b11011 "
#2060
b11100 "
#2062
b11101 "
#2064
b11110 "
#2066
0'
b11111 "
#2068
b1 #
b0 !
b0 "
#2070
b1 "
#2072
b10 "
#2074
b11 "
#2076
b100 "
#2078
b101 "
#2080
b110 "
#2082
b111 "
#2084
b1000 "
#2086
b1001 "
#2088
b1010 "
#2090
b1011 "
#2092
b1100 "
#2094
b1101 "
#2096
b1110 "
#2098
b1111 "
#2100
b10000 "
#2102
b10001 "
#2104
b10010 "
#2106
b10011 "
#2108
b10100 "
#2110
b10101 "
#2112
b10110 "
#2114
b10111 "
#2116
b11000 "
#2118
b11001 "
#2120
b11010 "
#2122
b11011 "
#2124
b11100 "
#2126
b11101 "
#2128
b11110 "
#2130
b11111 "
#2132
b1 !
b0 "
#2134
b1 "
#2136
b10 "
#2138
b11 "
#2140
b100 "
#2142
b101 "
#2144
b110 "
#2146
b111 "
#2148
b1000 "
#2150
b1001 "
#2152
b1010 "
#2154
b1011 "
#2156
b1100 "
#2158
b1101 "
#2160
b1110 "
#2162
b1111 "
#2164
b10000 "
#2166
b10001 "
#2168
b10010 "
#2170
b10011 "
#2172
b10100 "
#2174
b10101 "
#2176
b10110 "
#2178
b10111 "
#2180
b11000 "
#2182
b11001 "
#2184
b11010 "
#2186
b11011 "
#2188
b11100 "
#2190
b11101 "
#2192
b11110 "
#2194
b11111 "
#2196
b10 !
b0 "
#2198
b1 "
#2200
b10 "
#2202
b11 "
#2204
b100 "
#2206
b101 "
#2208
b110 "
#2210
b111 "
#2212
b1000 "
#2214
b1001 "
#2216
b1010 "
#2218
b1011 "
#2220
b1100 "
#2222
b1101 "
#2224
b1110 "
#2226
b1111 "
#2228
b10000 "
#2230
b10001 "
#2232
b10010 "
#2234
b10011 "
#2236
b10100 "
#2238
b10101 "
#2240
b10110 "
#2242
b10111 "
#2244
b11000 "
#2246
b11001 "
#2248
b11010 "
#2250
b11011 "
#2252
b11100 "
#2254
b11101 "
#2256
b11110 "
#2258
b11111 "
#2260
b11 !
b0 "
#2262
b1 "
#2264
b10 "
#2266
b11 "
#2268
b100 "
#2270
b101 "
#2272
b110 "
#2274
b111 "
#2276
b1000 "
#2278
b1001 "
#2280
b1010 "
#2282
b1011 "
#2284
b1100 "
#2286
b1101 "
#2288
b1110 "
#2290
b1111 "
#2292
b10000 "
#2294
b10001 "
#2296
b10010 "
#2298
b10011 "
#2300
b10100 "
#2302
b10101 "
#2304
b10110 "
#2306
b10111 "
#2308
b11000 "
#2310
b11001 "
#2312
b11010 "
#2314
b11011 "
#2316
b11100 "
#2318
b11101 "
#2320
b11110 "
#2322
b11111 "
#2324
b100 !
b0 "
#2326
b1 "
#2328
0$
b1 (
b10 "
#2330
b11 "
#2332
b10 (
b100 "
#2334
b101 "
#2336
b11 (
b110 "
#2338
b111 "
#2340
b100 (
b1000 "
#2342
b1001 "
#2344
b101 (
b1010 "
#2346
b1011 "
#2348
b110 (
b1100 "
#2350
b1101 "
#2352
b111 (
b1110 "
#2354
b1111 "
#2356
1$
b0 (
b10000 "
#2358
b10001 "
#2360
0$
b1 (
b10010 "
#2362
b10011 "
#2364
b10 (
b10100 "
#2366
b10101 "
#2368
b11 (
b10110 "
#2370
b10111 "
#2372
b100 (
b11000 "
#2374
b11001 "
#2376
b101 (
b11010 "
#2378
b11011 "
#2380
b110 (
b11100 "
#2382
b11101 "
#2384
b111 (
b11110 "
#2386
b11111 "
#2388
1$
b0 (
b101 !
b0 "
#2390
b1 "
#2392
0$
b1 (
b10 "
#2394
b11 "
#2396
b10 (
b100 "
#2398
b101 "
#2400
b11 (
b110 "
#2402
b111 "
#2404
b100 (
b1000 "
#2406
b1001 "
#2408
b101 (
b1010 "
#2410
b1011 "
#2412
b110 (
b1100 "
#2414
b1101 "
#2416
b111 (
b1110 "
#2418
b1111 "
#2420
1$
b0 (
b10000 "
#2422
b10001 "
#2424
0$
b1 (
b10010 "
#2426
b10011 "
#2428
b10 (
b10100 "
#2430
b10101 "
#2432
b11 (
b10110 "
#2434
b10111 "
#2436
b100 (
b11000 "
#2438
b11001 "
#2440
b101 (
b11010 "
#2442
b11011 "
#2444
b110 (
b11100 "
#2446
b11101 "
#2448
b111 (
b11110 "
#2450
b11111 "
#2452
1$
b0 (
b110 !
b0 "
#2454
b1 "
#2456
0$
b1 (
b10 "
#2458
b11 "
#2460
b10 (
b100 "
#2462
b101 "
#2464
b11 (
b110 "
#2466
b111 "
#2468
b100 (
b1000 "
#2470
b1001 "
#2472
b101 (
b1010 "
#2474
b1011 "
#2476
b110 (
b1100 "
#2478
b1101 "
#2480
b111 (
b1110 "
#2482
b1111 "
#2484
1$
b0 (
b10000 "
#2486
b10001 "
#2488
0$
b1 (
b10010 "
#2490
b10011 "
#2492
b10 (
b10100 "
#2494
b10101 "
#2496
b11 (
b10110 "
#2498
b10111 "
#2500
b100 (
b11000 "
#2502
b11001 "
#2504
b101 (
b11010 "
#2506
b11011 "
#2508
b110 (
b11100 "
#2510
b11101 "
#2512
b111 (
b11110 "
#2514
b11111 "
#2516
1$
b0 (
b111 !
b0 "
#2518
b1 "
#2520
0$
b1 (
b10 "
#2522
b11 "
#2524
b10 (
b100 "
#2526
b101 "
#2528
b11 (
b110 "
#2530
b111 "
#2532
b100 (
b1000 "
#2534
b1001 "
#2536
b101 (
b1010 "
#2538
b1011 "
#2540
b110 (
b1100 "
#2542
b1101 "
#2544
b111 (
b1110 "
#2546
b1111 "
#2548
1$
b0 (
b10000 "
#2550
b10001 "
#2552
0$
b1 (
b10010 "
#2554
b10011 "
#2556
b10 (
b10100 "
#2558
b10101 "
#2560
b11 (
b10110 "
#2562
b10111 "
#2564
b100 (
b11000 "
#2566
b11001 "
#2568
b101 (
b11010 "
#2570
b11011 "
#2572
b110 (
b11100 "
#2574
b11101 "
#2576
b111 (
b11110 "
#2578
b11111 "
#2580
1$
b0 (
b1000 !
b0 "
#2582
b1 "
#2584
0$
b10 (
b10 "
#2586
b11 "
#2588
b100 (
b100 "
#2590
b101 "
#2592
b110 (
b110 "
#2594
b111 "
#2596
b1000 (
b1000 "
#2598
b1001 "
#2600
b1010 (
b1010 "
#2602
b1011 "
#2604
b1100 (
b1100 "
#2606
b1101 "
#2608
b1110 (
b1110 "
#2610
b1111 "
#2612
1$
b0 (
b10000 "
#2614
b10001 "
#2616
0$
b10 (
b10010 "
#2618
b10011 "
#2620
b100 (
b10100 "
#2622
b10101 "
#2624
b110 (
b10110 "
#2626
b10111 "
#2628
b1000 (
b11000 "
#2630
b11001 "
#2632
b1010 (
b11010 "
#2634
b11011 "
#2636
b1100 (
b11100 "
#2638
b11101 "
#2640
b1110 (
b11110 "
#2642
b11111 "
#2644
1$
b0 (
b1001 !
b0 "
#2646
b1 "
#2648
0$
b10 (
b10 "
#2650
b11 "
#2652
b100 (
b100 "
#2654
b101 "
#2656
b110 (
b110 "
#2658
b111 "
#2660
b1000 (
b1000 "
#2662
b1001 "
#2664
b1010 (
b1010 "
#2666
b1011 "
#2668
b1100 (
b1100 "
#2670
b1101 "
#2672
b1110 (
b1110 "
#2674
b1111 "
#2676
1$
b0 (
b10000 "
#2678
b10001 "
#2680
0$
b10 (
b10010 "
#2682
b10011 "
#2684
b100 (
b10100 "
#2686
b10101 "
#2688
b110 (
b10110 "
#2690
b10111 "
#2692
b1000 (
b11000 "
#2694
b11001 "
#2696
b1010 (
b11010 "
#2698
b11011 "
#2700
b1100 (
b11100 "
#2702
b11101 "
#2704
b1110 (
b11110 "
#2706
b11111 "
#2708
1$
b0 (
b1010 !
b0 "
#2710
b1 "
#2712
0$
b10 (
b10 "
#2714
b11 "
#2716
b100 (
b100 "
#2718
b101 "
#2720
b110 (
b110 "
#2722
b111 "
#2724
b1000 (
b1000 "
#2726
b1001 "
